<Document accessor="public" category="Function" name="Create" declFile="GuiTypeDescriptorPredefined.h" declId="FB$vl::reflection::description::IValueList::Create@::vl::Ptr&lt;::vl::reflection::description::IValueList&gt;()[decl0]"><summary>Create an empty list.</summary><returns>The created list.</returns><signature><![CDATA[static Ptr<IValueList> Create(
);
]]></signature><seealsos><symbol name="Ptr" docId="vl::Ptr" declFile="Pointer.h" declId="NI$vl::Ptr"/><symbol name="IValueList" docId="vl::reflection::description::IValueList" declFile="GuiTypeDescriptorPredefined.h" declId="NI$vl::reflection::description::IValueList"/></seealsos></Document>