<Document symbolId="vl::reflection::DescriptableObject::SetInternalProperty@void(::vl::WString const &amp;, ::vl::Ptr&lt;::vl::Object&gt;)" accessor="public" category="Function" name="SetInternalProperty"><summary>Set an internal property of this object. This map is totally for customization.</summary><param name="name">Name of the property.</param><param name="value">Value of the internal property of this object.</param><signature><![CDATA[void(WString const &,
Ptr<Object>);
]]></signature></Document>