<Document symbolId="vl::reflection::description::Value::From@::vl::reflection::description::Value(::vl::Ptr&lt;::vl::reflection::description::IBoxedValue&gt;, ::vl::reflection::description::ITypeDescriptor *)" accessor="public" category="Function" name="From"><summary>Store a text.</summary><returns>The boxed value.</returns><param name="value">The text to store.</param><param name="type">The type that you expect to interpret the text.</param><signature><![CDATA[static Value From(
    Ptr<IBoxedValue> value,
    ITypeDescriptor * type
);
]]></signature><seealsos><symbol docId="vl::Ptr" declFile="Pointer.h" declId="NI$vl::Ptr"/><symbol declFile="GuiTypeDescriptor.h" declId="NI$vl::reflection::description::ITypeDescriptor"/><symbol declFile="GuiTypeDescriptor.h" declId="NI$vl::reflection::description::IBoxedValue"/><symbol docId="vl::reflection::description::Value" declFile="GuiTypeDescriptor.h" declId="NI$vl::reflection::description::Value"/></seealsos></Document>