<Document symbolId="vl::reflection::DescriptableObject::SetInternalProperty@void(::vl::WString const &amp;, ::vl::Ptr&lt;::vl::Object&gt;)" accessor="public" category="Function" name="SetInternalProperty"><summary>Set an internal property of this object. This map is totally for customization.</summary><param name="name">Name of the property.</param><param name="value">Value of the internal property of this object.</param><signature><![CDATA[void SetInternalProperty(
    WString const & name,
    Ptr<Object> value
);
]]></signature><seealsos><symbol docId="vl::Object" declFile="Basic.h" declId="NI$vl::Object"/><symbol docId="vl::Ptr" declFile="Pointer.h" declId="NI$vl::Ptr"/><symbol docId="vl::WString" declFile="String.h" declId="NI$vl::WString"/></seealsos></Document>