<Document accessor="public" category="Function" name="IsAvailable" declFile="Interfaces.h2" declId="FB$vl::stream::IStream::IsAvailable@bool()[decl0]"><summary>Test if the stream is <b>available</b>. For example, if you create a readable <symbol name="FileStream" docId="vl::stream::FileStream" declFile="FileStream.h" declId="NI$vl::stream::FileStream"/> giving a wrong file name, it will be unavailable.</summary><returns>Returns true if the stream is <b>available</b>.</returns><signature><![CDATA[bool IsAvailable(
) const;
]]></signature></Document>