<Document symbolId="vl::presentation::GuiResource::LoadPrecompiledBinary@::vl::Ptr&lt;::vl::presentation::GuiResource&gt;(::vl::stream::IStream &amp;)" accessor="public" category="Function" name="LoadPrecompiledBinary"><summary>Load a precompiled resource from a stream. This function will hit an assert if there are errors.</summary><returns>The loaded resource.</returns><param name="binaryStream">The stream.</param><signature><![CDATA[static Ptr<GuiResource>(stream::IStream &);
]]></signature></Document>