<Document accessor="public" category="Function" name="SaveToXml" declFile="GuiResource.h" declId="FB$vl::presentation::GuiResource::SaveToXml@::vl::Ptr&lt;::vl::parsing::xml::XmlDocument&gt;()[decl0]"><summary>Save the resource to xml.</summary><returns>The xml.</returns><signature><![CDATA[Ptr<parsing::xml::XmlDocument> SaveToXml(
);
]]></signature><seealsos><symbol name="Ptr" docId="vl::Ptr" declFile="Pointer.h" declId="NI$vl::Ptr"/><symbol name="XmlDocument" docId="vl::parsing::xml::XmlDocument" declFile="ParsingXml_Ast.h" declId="NI$vl::parsing::xml::XmlDocument"/></seealsos></Document>