<Document symbolId="vl::presentation::theme::ITheme" accessor="" category="Class" name="ITheme"><summary>Theme interface. A theme creates appropriate style controllers or style providers for default controls. Call <symbol docId="vl::presentation::theme::GetCurrentTheme@::vl::presentation::theme::ITheme *()" declFile="GuiThemeStyleFactory.h" declId="FB$vl::presentation::theme::GetCurrentTheme@::vl::presentation::theme::ITheme *()[decl0]"/> to access this interface.</summary><signature><![CDATA[class ITheme;
]]></signature><seealsos><symbol docId="vl::presentation::theme::ITheme" declFile="GuiThemeStyleFactory.h" declId="NI$vl::presentation::theme::ITheme"/></seealsos><basetypes><symbol docId="vl::reflection::Description" declFile="GuiTypeDescriptor.h" declId="NI$vl::reflection::Description"/><symbol docId="vl::reflection::IDescriptable" declFile="GuiTypeDescriptor.h" declId="NI$vl::reflection::IDescriptable"/></basetypes></Document>