<Document symbolId="vl::presentation::controls::IGuiPluginManager::AddPlugin@void(::vl::Ptr&lt;::vl::presentation::controls::IGuiPlugin&gt;)" accessor="public" category="Function" name="AddPlugin"><summary>Add a plugin before <symbol docId="vl::presentation::controls::IGuiPluginManager::Load@void()" declFile="GuiApplication.h" declId="FB$vl::presentation::controls::IGuiPluginManager::Load@void()[decl0]"/> is called.</summary><param name="plugin">The plugin.</param><signature><![CDATA[void AddPlugin(
    Ptr<IGuiPlugin> plugin
);
]]></signature><seealsos><symbol docId="vl::Ptr" declFile="Pointer.h" declId="NI$vl::Ptr"/><symbol docId="vl::presentation::controls::IGuiPlugin" declFile="GuiApplication.h" declId="NI$vl::presentation::controls::IGuiPlugin"/></seealsos></Document>