<Document symbolId="vl::presentation::INativeImageFrame::GetImage@::vl::presentation::INativeImage *()" accessor="public" category="Function" name="GetImage" declFile="GuiNativeWindow.h" declId="FB$vl::presentation::INativeImageFrame::GetImage@::vl::presentation::INativeImage *()[decl0]"><summary>
 Get the image that owns this frame.
 </summary><returns>The image that owns this frame.</returns><signature><![CDATA[INativeImage * GetImage(
);
]]></signature><seealsos><symbol name="INativeImage" docId="vl::presentation::INativeImage" declFile="GuiNativeWindow.h" declId="NI$vl::presentation::INativeImage"/></seealsos></Document>