<Document symbolId="vl::presentation::controls::list::TextItemProvider" accessor="" category="Class" name="TextItemProvider" declFile="GuiTextListControls.h" declId="NI$vl::presentation::controls::list::TextItemProvider"><summary>Item provider for <symbol name="GuiVirtualTextList" docId="vl::presentation::controls::GuiVirtualTextList" declFile="GuiTextListControls.h" declId="NI$vl::presentation::controls::GuiVirtualTextList"/> or <symbol name="GuiSelectableListControl" docId="vl::presentation::controls::GuiSelectableListControl" declFile="GuiListControls.h" declId="NI$vl::presentation::controls::GuiSelectableListControl"/>.</summary><signature><![CDATA[class TextItemProvider
    : ListProvider<Ptr<TextItem>>
    , ITextItemView
    , Description<TextItemProvider>;
]]></signature><seealsos><symbol name="Ptr" docId="vl::Ptr" declFile="Pointer.h" declId="NI$vl::Ptr"/><symbol name="TextItem" docId="vl::presentation::controls::list::TextItem" declFile="GuiTextListControls.h" declId="NI$vl::presentation::controls::list::TextItem"/><symbol name="TextItemProvider" docId="vl::presentation::controls::list::TextItemProvider" declFile="GuiTextListControls.h" declId="NI$vl::presentation::controls::list::TextItemProvider"/></seealsos><basetypes><symbol name="ITextItemView" docId="vl::presentation::controls::list::ITextItemView" declFile="GuiTextListControls.h" declId="NI$vl::presentation::controls::list::ITextItemView"/><symbol name="ListProvider" declFile="GuiListControls.h" declId="NI$vl::presentation::controls::list::ListProvider"/><symbol name="Description" docId="vl::reflection::Description" declFile="GuiTypeDescriptor.h" declId="NI$vl::reflection::Description"/></basetypes></Document>