<Document accessor="public" category="Function" name="NativeWindowDestroying" declFile="GuiNativeWindow.h" declId="FB$vl::presentation::INativeControllerListener::NativeWindowDestroying@void(::vl::presentation::INativeWindow *)[decl0]"><summary>
 Called when a window is destroying.
 </summary><param name="window">The destroying window.</param><signature><![CDATA[void NativeWindowDestroying(
    INativeWindow * window
);
]]></signature><seealsos><symbol name="INativeWindow" docId="vl::presentation::INativeWindow" declFile="GuiNativeWindow.h" declId="NI$vl::presentation::INativeWindow"/></seealsos></Document>