<Document symbolId="vl::presentation::controls::list::FixedSizeMultiColumnItemArranger" accessor="" category="Class" name="FixedSizeMultiColumnItemArranger" declFile="GuiListControlItemArrangers.h" declId="NI$vl::presentation::controls::list::FixedSizeMultiColumnItemArranger"><summary>Fixed size multiple columns item arranger. This arranger adjust all items in multiple lines with the same size. The width is the maximum width of all minimum widths of displayed items. The same to height.</summary><signature><![CDATA[class FixedSizeMultiColumnItemArranger
    : RangedItemArrangerBase
    , Description<FixedSizeMultiColumnItemArranger>;
]]></signature><seealsos><symbol name="FixedSizeMultiColumnItemArranger" docId="vl::presentation::controls::list::FixedSizeMultiColumnItemArranger" declFile="GuiListControlItemArrangers.h" declId="NI$vl::presentation::controls::list::FixedSizeMultiColumnItemArranger"/></seealsos><basetypes><symbol name="RangedItemArrangerBase" docId="vl::presentation::controls::list::RangedItemArrangerBase" declFile="GuiListControlItemArrangers.h" declId="NI$vl::presentation::controls::list::RangedItemArrangerBase"/><symbol name="Description" docId="vl::reflection::Description" declFile="GuiTypeDescriptor.h" declId="NI$vl::reflection::Description"/></basetypes></Document>