<Document symbolId="vl::presentation::compositions::GuiGraphicsComposition::GetOwnedElement@::vl::Ptr&lt;::vl::presentation::elements::IGuiGraphicsElement&gt;()" accessor="public" category="Function" name="GetOwnedElement" declFile="GuiGraphicsCompositionBase.h" declId="FB$vl::presentation::compositions::GuiGraphicsComposition::GetOwnedElement@::vl::Ptr&lt;::vl::presentation::elements::IGuiGraphicsElement&gt;()[decl0]"><summary>Get the contained graphics element.</summary><returns>The contained graphics element.</returns><signature><![CDATA[Ptr<elements::IGuiGraphicsElement> GetOwnedElement(
);
]]></signature><seealsos><symbol name="Ptr" docId="vl::Ptr" declFile="Pointer.h" declId="NI$vl::Ptr"/><symbol name="IGuiGraphicsElement" docId="vl::presentation::elements::IGuiGraphicsElement" declFile="GuiGraphicsElementInterfaces.h" declId="NI$vl::presentation::elements::IGuiGraphicsElement"/></seealsos></Document>