<Document symbolId="vl::presentation::elements::Gui3DSplitterElement::SetColor2@void(::vl::presentation::Color)" accessor="public" category="Function" name="SetColor2" declFile="GuiGraphicsElement.h" declId="FB$vl::presentation::elements::Gui3DSplitterElement::SetColor2@void(::vl::presentation::Color)[decl0]"><summary>
 Set the border color.
 </summary><param name="value">The new right-bottom color.</param><signature><![CDATA[void SetColor2(
    Color value
);
]]></signature><seealsos><symbol name="Color" docId="vl::presentation::Color" declFile="GuiTypes.h" declId="NI$vl::presentation::Color"/></seealsos></Document>