<Document symbolId="vl::presentation::IGuiResourceTypeResolver_DirectLoadStream::ResolveResourcePrecompiled@::vl::Ptr&lt;::vl::reflection::DescriptableObject&gt;(::vl::Ptr&lt;::vl::presentation::GuiResourceItem&gt;, ::vl::stream::IStream &amp;, ::vl::presentation::GuiResourceError::List &amp;)" accessor="public" category="Function" name="ResolveResourcePrecompiled"><summary>Load a precompiled resource from a stream.</summary><returns>The resource.</returns><param name="resource">The resource item containing the resource.</param><param name="binaryStream">The stream.</param><param name="errors">All collected errors during loading a resource.</param><signature><![CDATA[Ptr<DescriptableObject> ResolveResourcePrecompiled(
    Ptr<GuiResourceItem>,
    stream::IStream &,
    GuiResourceError::List &
);
]]></signature></Document>