<Document symbolId="vl::presentation::controls::GuiDocumentCommonInterface::RemoveStyleName@void(::vl::presentation::TextPos, ::vl::presentation::TextPos)" accessor="public" category="Function" name="RemoveStyleName" declFile="GuiDocumentViewer.h" declId="FB$vl::presentation::controls::GuiDocumentCommonInterface::RemoveStyleName@void(::vl::presentation::TextPos, ::vl::presentation::TextPos)[decl0]"><summary>Remove style name in a specified range.</summary><param name="begin">The begin position of the range.</param><param name="end">The end position of the range.</param><signature><![CDATA[void RemoveStyleName(
    TextPos begin,
    TextPos end
);
]]></signature><seealsos><symbol name="TextPos" docId="vl::presentation::TextPos" declFile="GuiTypes.h" declId="NI$vl::presentation::TextPos"/></seealsos></Document>