<Document accessor="public" category="Variable" name="duplicatedTypes" declFile="WfRuntimeAssembly.h" declId="NI$vl::workflow::runtime::WfAssemblyLoadErrors::duplicatedTypes"><summary>All duplicated types. Types are shared in the process, there is no isolation between assemblies.</summary><signature><![CDATA[collections::List<WString> duplicatedTypes;
]]></signature><seealsos><symbol name="WString" docId="vl::WString" declFile="String.h" declId="NI$vl::WString"/><symbol name="List" docId="vl::collections::List" declFile="List.h" declId="NI$vl::collections::List"/></seealsos></Document>