<Document symbolId="vl::workflow::runtime::WfRuntimeCallStackInfo::arguments" accessor="public" category="Variable" name="arguments" declFile="WfRuntime.h" declId="NI$vl::workflow::runtime::WfRuntimeCallStackInfo::arguments"><summary>Argument values.</summary><signature><![CDATA[Ptr<WfRuntimeVariableContext> arguments;
]]></signature><seealsos><symbol name="Ptr" docId="vl::Ptr" declFile="Pointer.h" declId="NI$vl::Ptr"/><symbol name="WfRuntimeVariableContext" declFile="WfRuntime.h" declId="NI$vl::workflow::runtime::WfRuntimeVariableContext"/></seealsos></Document>