<Document symbolId="vl::workflow::runtime::GetDebuggerForCurrentThread@::vl::Ptr&lt;::vl::workflow::runtime::WfDebugger&gt;()" accessor="" category="Function" name="GetDebuggerForCurrentThread" declFile="WfRuntimeDebugger.h" declId="FB$vl::workflow::runtime::GetDebuggerForCurrentThread@::vl::Ptr&lt;::vl::workflow::runtime::WfDebugger&gt;()[decl0]"><summary>Get the debugger for the current thread.</summary><returns>The debugger.</returns><signature><![CDATA[Ptr<WfDebugger> GetDebuggerForCurrentThread(
);
]]></signature><seealsos><symbol name="Ptr" docId="vl::Ptr" declFile="Pointer.h" declId="NI$vl::Ptr"/><symbol name="WfDebugger" docId="vl::workflow::runtime::WfDebugger" declFile="WfRuntimeDebugger.h" declId="NI$vl::workflow::runtime::WfDebugger"/></seealsos></Document>