<Document symbolId="vl::workflow::runtime::WfAssembly::functions" accessor="public" category="Variable" name="functions" declFile="WfRuntimeAssembly.h" declId="NI$vl::workflow::runtime::WfAssembly::functions"><summary>Functions.</summary><signature><![CDATA[collections::List<Ptr<WfAssemblyFunction>> functions;
]]></signature><seealsos><symbol name="Ptr" docId="vl::Ptr" declFile="Pointer.h" declId="NI$vl::Ptr"/><symbol name="List" docId="vl::collections::List" declFile="List.h" declId="NI$vl::collections::List"/><symbol name="WfAssemblyFunction" docId="vl::workflow::runtime::WfAssemblyFunction" declFile="WfRuntimeAssembly.h" declId="NI$vl::workflow::runtime::WfAssemblyFunction"/></seealsos></Document>