<Document accessor="public" category="Function" name="GetPathResolverFactory"><summary>Get the <symbol name="IGuiResourcePathResolverFactory" docId="vl::presentation::IGuiResourcePathResolverFactory"/> for a protocol.</summary><returns>The factory.</returns><param name="protocol">The protocol.</param><signature><![CDATA[IGuiResourcePathResolverFactory * GetPathResolverFactory(
    WString const & protocol
);
]]></signature><seealsos><symbol name="WString" docId="vl::WString"/><symbol name="IGuiResourcePathResolverFactory" docId="vl::presentation::IGuiResourcePathResolverFactory"/></seealsos></Document>